[
    {
        "businessPartnerId": "zdchsxtSFjNkVBuiMnuUoGWerqqfdWrQ",
        "name1": "name11",
        "name2": "name21",
        "name3": "name31",
        "name4": "name41",
        "emailAddress": "emailAddress1",
        "phoneNumber": "phoneNumber1",
        "cellPhoneNumber": "cellPhoneNumber1",
        "faxNumber": "faxNumber1",
        "country": "country1",
        "region": "region1",
        "cityName": "cityName1",
        "postalCode": "postalCode1",
        "streetName": "streetName1"
    },
    {
        "businessPartnerId": "fjFMUoeRiraecyEeWKZTBFgTTzFRRywI",
        "name1": "name12",
        "name2": "name22",
        "name3": "name32",
        "name4": "name42",
        "emailAddress": "emailAddress2",
        "phoneNumber": "phoneNumber2",
        "cellPhoneNumber": "cellPhoneNumber2",
        "faxNumber": "faxNumber2",
        "country": "country2",
        "region": "region2",
        "cityName": "cityName2",
        "postalCode": "postalCode2",
        "streetName": "streetName2"
    },
    {
        "businessPartnerId": "YqsCYPKiMOizmqHsJfvJanoJOJYXgxOW",
        "name1": "name13",
        "name2": "name23",
        "name3": "name33",
        "name4": "name43",
        "emailAddress": "emailAddress3",
        "phoneNumber": "phoneNumber3",
        "cellPhoneNumber": "cellPhoneNumber3",
        "faxNumber": "faxNumber3",
        "country": "country3",
        "region": "region3",
        "cityName": "cityName3",
        "postalCode": "postalCode3",
        "streetName": "streetName3"
    },
    {
        "businessPartnerId": "PCVJTLNripyEemlFVeayCOSZoBSXPDec",
        "name1": "name14",
        "name2": "name24",
        "name3": "name34",
        "name4": "name44",
        "emailAddress": "emailAddress4",
        "phoneNumber": "phoneNumber4",
        "cellPhoneNumber": "cellPhoneNumber4",
        "faxNumber": "faxNumber4",
        "country": "country4",
        "region": "region4",
        "cityName": "cityName4",
        "postalCode": "postalCode4",
        "streetName": "streetName4"
    },
    {
        "businessPartnerId": "YYxUQNcgOkZNgysDagHZvjGVjnVMSUzT",
        "name1": "name15",
        "name2": "name25",
        "name3": "name35",
        "name4": "name45",
        "emailAddress": "emailAddress5",
        "phoneNumber": "phoneNumber5",
        "cellPhoneNumber": "cellPhoneNumber5",
        "faxNumber": "faxNumber5",
        "country": "country5",
        "region": "region5",
        "cityName": "cityName5",
        "postalCode": "postalCode5",
        "streetName": "streetName5"
    },
    {
        "businessPartnerId": "VBPaYGDfpjOCDpprSPnOJjvrIoHDgFht",
        "name1": "name16",
        "name2": "name26",
        "name3": "name36",
        "name4": "name46",
        "emailAddress": "emailAddress6",
        "phoneNumber": "phoneNumber6",
        "cellPhoneNumber": "cellPhoneNumber6",
        "faxNumber": "faxNumber6",
        "country": "country6",
        "region": "region6",
        "cityName": "cityName6",
        "postalCode": "postalCode6",
        "streetName": "streetName6"
    },
    {
        "businessPartnerId": "qejfGZUGqTWjGKnERpifLbdYcZpbnbKq",
        "name1": "name17",
        "name2": "name27",
        "name3": "name37",
        "name4": "name47",
        "emailAddress": "emailAddress7",
        "phoneNumber": "phoneNumber7",
        "cellPhoneNumber": "cellPhoneNumber7",
        "faxNumber": "faxNumber7",
        "country": "country7",
        "region": "region7",
        "cityName": "cityName7",
        "postalCode": "postalCode7",
        "streetName": "streetName7"
    },
    {
        "businessPartnerId": "EPfHnBiXiqQuImihUkrSQWlAqtxRPyZu",
        "name1": "name18",
        "name2": "name28",
        "name3": "name38",
        "name4": "name48",
        "emailAddress": "emailAddress8",
        "phoneNumber": "phoneNumber8",
        "cellPhoneNumber": "cellPhoneNumber8",
        "faxNumber": "faxNumber8",
        "country": "country8",
        "region": "region8",
        "cityName": "cityName8",
        "postalCode": "postalCode8",
        "streetName": "streetName8"
    },
    {
        "businessPartnerId": "UppoYzIvHJXJrOEDrKKxjsSssZcwPQXm",
        "name1": "name19",
        "name2": "name29",
        "name3": "name39",
        "name4": "name49",
        "emailAddress": "emailAddress9",
        "phoneNumber": "phoneNumber9",
        "cellPhoneNumber": "cellPhoneNumber9",
        "faxNumber": "faxNumber9",
        "country": "country9",
        "region": "region9",
        "cityName": "cityName9",
        "postalCode": "postalCode9",
        "streetName": "streetName9"
    },
    {
        "businessPartnerId": "TcNhaiwLJFKcowiGTxeEkdxDYYLvBWjO",
        "name1": "name110",
        "name2": "name210",
        "name3": "name310",
        "name4": "name410",
        "emailAddress": "emailAddress10",
        "phoneNumber": "phoneNumber10",
        "cellPhoneNumber": "cellPhoneNumber10",
        "faxNumber": "faxNumber10",
        "country": "country10",
        "region": "region10",
        "cityName": "cityName10",
        "postalCode": "postalCode10",
        "streetName": "streetName10"
    },
    {
        "businessPartnerId": "NNChvjurIXUnXdeVgEXHTvTeCGkgihiu",
        "name1": "name111",
        "name2": "name211",
        "name3": "name311",
        "name4": "name411",
        "emailAddress": "emailAddress11",
        "phoneNumber": "phoneNumber11",
        "cellPhoneNumber": "cellPhoneNumber11",
        "faxNumber": "faxNumber11",
        "country": "country11",
        "region": "region11",
        "cityName": "cityName11",
        "postalCode": "postalCode11",
        "streetName": "streetName11"
    },
    {
        "businessPartnerId": "ULRRUJQJkEodSyfqgHBQlswoyiCOeKsh",
        "name1": "name112",
        "name2": "name212",
        "name3": "name312",
        "name4": "name412",
        "emailAddress": "emailAddress12",
        "phoneNumber": "phoneNumber12",
        "cellPhoneNumber": "cellPhoneNumber12",
        "faxNumber": "faxNumber12",
        "country": "country12",
        "region": "region12",
        "cityName": "cityName12",
        "postalCode": "postalCode12",
        "streetName": "streetName12"
    },
    {
        "businessPartnerId": "uemsbGlsBBeVCqxArkauwfklSSbctzea",
        "name1": "name113",
        "name2": "name213",
        "name3": "name313",
        "name4": "name413",
        "emailAddress": "emailAddress13",
        "phoneNumber": "phoneNumber13",
        "cellPhoneNumber": "cellPhoneNumber13",
        "faxNumber": "faxNumber13",
        "country": "country13",
        "region": "region13",
        "cityName": "cityName13",
        "postalCode": "postalCode13",
        "streetName": "streetName13"
    },
    {
        "businessPartnerId": "uBfNTiKKkfnvnsSuNdeAdAqtFLxrTqQl",
        "name1": "name114",
        "name2": "name214",
        "name3": "name314",
        "name4": "name414",
        "emailAddress": "emailAddress14",
        "phoneNumber": "phoneNumber14",
        "cellPhoneNumber": "cellPhoneNumber14",
        "faxNumber": "faxNumber14",
        "country": "country14",
        "region": "region14",
        "cityName": "cityName14",
        "postalCode": "postalCode14",
        "streetName": "streetName14"
    },
    {
        "businessPartnerId": "fmYGXSpDsSvOwEWoThrFxXsXlvRLqKHz",
        "name1": "name115",
        "name2": "name215",
        "name3": "name315",
        "name4": "name415",
        "emailAddress": "emailAddress15",
        "phoneNumber": "phoneNumber15",
        "cellPhoneNumber": "cellPhoneNumber15",
        "faxNumber": "faxNumber15",
        "country": "country15",
        "region": "region15",
        "cityName": "cityName15",
        "postalCode": "postalCode15",
        "streetName": "streetName15"
    },
    {
        "businessPartnerId": "WAMOxHdLqDBtOQseLyjilxpBponLmVnM",
        "name1": "name116",
        "name2": "name216",
        "name3": "name316",
        "name4": "name416",
        "emailAddress": "emailAddress16",
        "phoneNumber": "phoneNumber16",
        "cellPhoneNumber": "cellPhoneNumber16",
        "faxNumber": "faxNumber16",
        "country": "country16",
        "region": "region16",
        "cityName": "cityName16",
        "postalCode": "postalCode16",
        "streetName": "streetName16"
    },
    {
        "businessPartnerId": "KrxoKTIKFEjvQHugYsiVpgCHJvxsdIAA",
        "name1": "name117",
        "name2": "name217",
        "name3": "name317",
        "name4": "name417",
        "emailAddress": "emailAddress17",
        "phoneNumber": "phoneNumber17",
        "cellPhoneNumber": "cellPhoneNumber17",
        "faxNumber": "faxNumber17",
        "country": "country17",
        "region": "region17",
        "cityName": "cityName17",
        "postalCode": "postalCode17",
        "streetName": "streetName17"
    },
    {
        "businessPartnerId": "WcqheIZecYwKwjeNcwgEMVqGHVyBBKxQ",
        "name1": "name118",
        "name2": "name218",
        "name3": "name318",
        "name4": "name418",
        "emailAddress": "emailAddress18",
        "phoneNumber": "phoneNumber18",
        "cellPhoneNumber": "cellPhoneNumber18",
        "faxNumber": "faxNumber18",
        "country": "country18",
        "region": "region18",
        "cityName": "cityName18",
        "postalCode": "postalCode18",
        "streetName": "streetName18"
    },
    {
        "businessPartnerId": "LPZkMFYiIkfivitqLRoMwsiNIydtvFhp",
        "name1": "name119",
        "name2": "name219",
        "name3": "name319",
        "name4": "name419",
        "emailAddress": "emailAddress19",
        "phoneNumber": "phoneNumber19",
        "cellPhoneNumber": "cellPhoneNumber19",
        "faxNumber": "faxNumber19",
        "country": "country19",
        "region": "region19",
        "cityName": "cityName19",
        "postalCode": "postalCode19",
        "streetName": "streetName19"
    },
    {
        "businessPartnerId": "NDFOvXnoZGsRcjkIpWrsteoelfkygOHN",
        "name1": "name120",
        "name2": "name220",
        "name3": "name320",
        "name4": "name420",
        "emailAddress": "emailAddress20",
        "phoneNumber": "phoneNumber20",
        "cellPhoneNumber": "cellPhoneNumber20",
        "faxNumber": "faxNumber20",
        "country": "country20",
        "region": "region20",
        "cityName": "cityName20",
        "postalCode": "postalCode20",
        "streetName": "streetName20"
    },
    {
        "businessPartnerId": "XUGfOcpylipOjwTWKbDniiYtxjMxdBkJ",
        "name1": "name121",
        "name2": "name221",
        "name3": "name321",
        "name4": "name421",
        "emailAddress": "emailAddress21",
        "phoneNumber": "phoneNumber21",
        "cellPhoneNumber": "cellPhoneNumber21",
        "faxNumber": "faxNumber21",
        "country": "country21",
        "region": "region21",
        "cityName": "cityName21",
        "postalCode": "postalCode21",
        "streetName": "streetName21"
    },
    {
        "businessPartnerId": "ckXgExgnpWmZwIIDgoACQzpgZnlbZhMg",
        "name1": "name122",
        "name2": "name222",
        "name3": "name322",
        "name4": "name422",
        "emailAddress": "emailAddress22",
        "phoneNumber": "phoneNumber22",
        "cellPhoneNumber": "cellPhoneNumber22",
        "faxNumber": "faxNumber22",
        "country": "country22",
        "region": "region22",
        "cityName": "cityName22",
        "postalCode": "postalCode22",
        "streetName": "streetName22"
    },
    {
        "businessPartnerId": "SKEYsyASCatoAplWmHKoPXWFBZHKkuAg",
        "name1": "name123",
        "name2": "name223",
        "name3": "name323",
        "name4": "name423",
        "emailAddress": "emailAddress23",
        "phoneNumber": "phoneNumber23",
        "cellPhoneNumber": "cellPhoneNumber23",
        "faxNumber": "faxNumber23",
        "country": "country23",
        "region": "region23",
        "cityName": "cityName23",
        "postalCode": "postalCode23",
        "streetName": "streetName23"
    },
    {
        "businessPartnerId": "KWzbsDymbxkNAhlIAxHvCpussUPNupuh",
        "name1": "name124",
        "name2": "name224",
        "name3": "name324",
        "name4": "name424",
        "emailAddress": "emailAddress24",
        "phoneNumber": "phoneNumber24",
        "cellPhoneNumber": "cellPhoneNumber24",
        "faxNumber": "faxNumber24",
        "country": "country24",
        "region": "region24",
        "cityName": "cityName24",
        "postalCode": "postalCode24",
        "streetName": "streetName24"
    },
    {
        "businessPartnerId": "IZDzAoRtikwAtuNRdHITEtrUoEXrzutu",
        "name1": "name125",
        "name2": "name225",
        "name3": "name325",
        "name4": "name425",
        "emailAddress": "emailAddress25",
        "phoneNumber": "phoneNumber25",
        "cellPhoneNumber": "cellPhoneNumber25",
        "faxNumber": "faxNumber25",
        "country": "country25",
        "region": "region25",
        "cityName": "cityName25",
        "postalCode": "postalCode25",
        "streetName": "streetName25"
    },
    {
        "businessPartnerId": "meFmaPMiziWCiVDOujxyWMPVOQyhLIEJ",
        "name1": "name126",
        "name2": "name226",
        "name3": "name326",
        "name4": "name426",
        "emailAddress": "emailAddress26",
        "phoneNumber": "phoneNumber26",
        "cellPhoneNumber": "cellPhoneNumber26",
        "faxNumber": "faxNumber26",
        "country": "country26",
        "region": "region26",
        "cityName": "cityName26",
        "postalCode": "postalCode26",
        "streetName": "streetName26"
    },
    {
        "businessPartnerId": "lRayBeepHlrVFkrPVpQXgxzezVDmeYjF",
        "name1": "name127",
        "name2": "name227",
        "name3": "name327",
        "name4": "name427",
        "emailAddress": "emailAddress27",
        "phoneNumber": "phoneNumber27",
        "cellPhoneNumber": "cellPhoneNumber27",
        "faxNumber": "faxNumber27",
        "country": "country27",
        "region": "region27",
        "cityName": "cityName27",
        "postalCode": "postalCode27",
        "streetName": "streetName27"
    },
    {
        "businessPartnerId": "UKyibxXGeRXTriNOBgDaLXZWSkyjeiSg",
        "name1": "name128",
        "name2": "name228",
        "name3": "name328",
        "name4": "name428",
        "emailAddress": "emailAddress28",
        "phoneNumber": "phoneNumber28",
        "cellPhoneNumber": "cellPhoneNumber28",
        "faxNumber": "faxNumber28",
        "country": "country28",
        "region": "region28",
        "cityName": "cityName28",
        "postalCode": "postalCode28",
        "streetName": "streetName28"
    },
    {
        "businessPartnerId": "KXIkYSNYtXFWehOiXYcdoyKZHtFEapGR",
        "name1": "name129",
        "name2": "name229",
        "name3": "name329",
        "name4": "name429",
        "emailAddress": "emailAddress29",
        "phoneNumber": "phoneNumber29",
        "cellPhoneNumber": "cellPhoneNumber29",
        "faxNumber": "faxNumber29",
        "country": "country29",
        "region": "region29",
        "cityName": "cityName29",
        "postalCode": "postalCode29",
        "streetName": "streetName29"
    },
    {
        "businessPartnerId": "UNzynkIBxlVTaGluisAVtAHEwBNGXrDN",
        "name1": "name130",
        "name2": "name230",
        "name3": "name330",
        "name4": "name430",
        "emailAddress": "emailAddress30",
        "phoneNumber": "phoneNumber30",
        "cellPhoneNumber": "cellPhoneNumber30",
        "faxNumber": "faxNumber30",
        "country": "country30",
        "region": "region30",
        "cityName": "cityName30",
        "postalCode": "postalCode30",
        "streetName": "streetName30"
    },
    {
        "businessPartnerId": "XKDGoaLyqTkXAhHILCdCqYAXnUtOSuCl",
        "name1": "name131",
        "name2": "name231",
        "name3": "name331",
        "name4": "name431",
        "emailAddress": "emailAddress31",
        "phoneNumber": "phoneNumber31",
        "cellPhoneNumber": "cellPhoneNumber31",
        "faxNumber": "faxNumber31",
        "country": "country31",
        "region": "region31",
        "cityName": "cityName31",
        "postalCode": "postalCode31",
        "streetName": "streetName31"
    },
    {
        "businessPartnerId": "pyJCbMkGQnQPmDkZHQSEhOdTHyNTXSvT",
        "name1": "name132",
        "name2": "name232",
        "name3": "name332",
        "name4": "name432",
        "emailAddress": "emailAddress32",
        "phoneNumber": "phoneNumber32",
        "cellPhoneNumber": "cellPhoneNumber32",
        "faxNumber": "faxNumber32",
        "country": "country32",
        "region": "region32",
        "cityName": "cityName32",
        "postalCode": "postalCode32",
        "streetName": "streetName32"
    },
    {
        "businessPartnerId": "HwnodcsSRBiGovMCpaffjpLIHFElWtnr",
        "name1": "name133",
        "name2": "name233",
        "name3": "name333",
        "name4": "name433",
        "emailAddress": "emailAddress33",
        "phoneNumber": "phoneNumber33",
        "cellPhoneNumber": "cellPhoneNumber33",
        "faxNumber": "faxNumber33",
        "country": "country33",
        "region": "region33",
        "cityName": "cityName33",
        "postalCode": "postalCode33",
        "streetName": "streetName33"
    },
    {
        "businessPartnerId": "nYGIxYwrZiCLtACQOourOEVXZIvSApdJ",
        "name1": "name134",
        "name2": "name234",
        "name3": "name334",
        "name4": "name434",
        "emailAddress": "emailAddress34",
        "phoneNumber": "phoneNumber34",
        "cellPhoneNumber": "cellPhoneNumber34",
        "faxNumber": "faxNumber34",
        "country": "country34",
        "region": "region34",
        "cityName": "cityName34",
        "postalCode": "postalCode34",
        "streetName": "streetName34"
    },
    {
        "businessPartnerId": "HibcQZcqRSQBNhrmXKCjJfOzDSmYJkPI",
        "name1": "name135",
        "name2": "name235",
        "name3": "name335",
        "name4": "name435",
        "emailAddress": "emailAddress35",
        "phoneNumber": "phoneNumber35",
        "cellPhoneNumber": "cellPhoneNumber35",
        "faxNumber": "faxNumber35",
        "country": "country35",
        "region": "region35",
        "cityName": "cityName35",
        "postalCode": "postalCode35",
        "streetName": "streetName35"
    },
    {
        "businessPartnerId": "cgdZvhlYIKROBPshCpIFCZmckiAHqSkQ",
        "name1": "name136",
        "name2": "name236",
        "name3": "name336",
        "name4": "name436",
        "emailAddress": "emailAddress36",
        "phoneNumber": "phoneNumber36",
        "cellPhoneNumber": "cellPhoneNumber36",
        "faxNumber": "faxNumber36",
        "country": "country36",
        "region": "region36",
        "cityName": "cityName36",
        "postalCode": "postalCode36",
        "streetName": "streetName36"
    },
    {
        "businessPartnerId": "cLGlAkhIMkPYyqIlfoggjqnQlrQNdolA",
        "name1": "name137",
        "name2": "name237",
        "name3": "name337",
        "name4": "name437",
        "emailAddress": "emailAddress37",
        "phoneNumber": "phoneNumber37",
        "cellPhoneNumber": "cellPhoneNumber37",
        "faxNumber": "faxNumber37",
        "country": "country37",
        "region": "region37",
        "cityName": "cityName37",
        "postalCode": "postalCode37",
        "streetName": "streetName37"
    },
    {
        "businessPartnerId": "dKqjUsgdmBtrhuvpydPGKiPQbqjjSDqq",
        "name1": "name138",
        "name2": "name238",
        "name3": "name338",
        "name4": "name438",
        "emailAddress": "emailAddress38",
        "phoneNumber": "phoneNumber38",
        "cellPhoneNumber": "cellPhoneNumber38",
        "faxNumber": "faxNumber38",
        "country": "country38",
        "region": "region38",
        "cityName": "cityName38",
        "postalCode": "postalCode38",
        "streetName": "streetName38"
    },
    {
        "businessPartnerId": "fTkNEoxEZIHkxMyDjJAKZyxidxPbNsWd",
        "name1": "name139",
        "name2": "name239",
        "name3": "name339",
        "name4": "name439",
        "emailAddress": "emailAddress39",
        "phoneNumber": "phoneNumber39",
        "cellPhoneNumber": "cellPhoneNumber39",
        "faxNumber": "faxNumber39",
        "country": "country39",
        "region": "region39",
        "cityName": "cityName39",
        "postalCode": "postalCode39",
        "streetName": "streetName39"
    },
    {
        "businessPartnerId": "tGsuOMLGnPNkqqjwLORooSfMbjCXJFSX",
        "name1": "name140",
        "name2": "name240",
        "name3": "name340",
        "name4": "name440",
        "emailAddress": "emailAddress40",
        "phoneNumber": "phoneNumber40",
        "cellPhoneNumber": "cellPhoneNumber40",
        "faxNumber": "faxNumber40",
        "country": "country40",
        "region": "region40",
        "cityName": "cityName40",
        "postalCode": "postalCode40",
        "streetName": "streetName40"
    },
    {
        "businessPartnerId": "qCwQVudbLuzmMQvimgcNbVHVMyRzMaxt",
        "name1": "name141",
        "name2": "name241",
        "name3": "name341",
        "name4": "name441",
        "emailAddress": "emailAddress41",
        "phoneNumber": "phoneNumber41",
        "cellPhoneNumber": "cellPhoneNumber41",
        "faxNumber": "faxNumber41",
        "country": "country41",
        "region": "region41",
        "cityName": "cityName41",
        "postalCode": "postalCode41",
        "streetName": "streetName41"
    },
    {
        "businessPartnerId": "LYhqivSiaZiOqotrQnSSXqDYbyzdLtny",
        "name1": "name142",
        "name2": "name242",
        "name3": "name342",
        "name4": "name442",
        "emailAddress": "emailAddress42",
        "phoneNumber": "phoneNumber42",
        "cellPhoneNumber": "cellPhoneNumber42",
        "faxNumber": "faxNumber42",
        "country": "country42",
        "region": "region42",
        "cityName": "cityName42",
        "postalCode": "postalCode42",
        "streetName": "streetName42"
    },
    {
        "businessPartnerId": "mioCtFoALdJkcIboRWEzqfCysIQmlHAz",
        "name1": "name143",
        "name2": "name243",
        "name3": "name343",
        "name4": "name443",
        "emailAddress": "emailAddress43",
        "phoneNumber": "phoneNumber43",
        "cellPhoneNumber": "cellPhoneNumber43",
        "faxNumber": "faxNumber43",
        "country": "country43",
        "region": "region43",
        "cityName": "cityName43",
        "postalCode": "postalCode43",
        "streetName": "streetName43"
    },
    {
        "businessPartnerId": "XjKTzhnrzLeDnpwjOlpZLqPrpOowhiLa",
        "name1": "name144",
        "name2": "name244",
        "name3": "name344",
        "name4": "name444",
        "emailAddress": "emailAddress44",
        "phoneNumber": "phoneNumber44",
        "cellPhoneNumber": "cellPhoneNumber44",
        "faxNumber": "faxNumber44",
        "country": "country44",
        "region": "region44",
        "cityName": "cityName44",
        "postalCode": "postalCode44",
        "streetName": "streetName44"
    },
    {
        "businessPartnerId": "ZPWTTtuQeWbOQoinqOBkvgQklfDJEKuT",
        "name1": "name145",
        "name2": "name245",
        "name3": "name345",
        "name4": "name445",
        "emailAddress": "emailAddress45",
        "phoneNumber": "phoneNumber45",
        "cellPhoneNumber": "cellPhoneNumber45",
        "faxNumber": "faxNumber45",
        "country": "country45",
        "region": "region45",
        "cityName": "cityName45",
        "postalCode": "postalCode45",
        "streetName": "streetName45"
    },
    {
        "businessPartnerId": "ARSOgTewmKQAVqWfpaaeUKrzIRebMzSX",
        "name1": "name146",
        "name2": "name246",
        "name3": "name346",
        "name4": "name446",
        "emailAddress": "emailAddress46",
        "phoneNumber": "phoneNumber46",
        "cellPhoneNumber": "cellPhoneNumber46",
        "faxNumber": "faxNumber46",
        "country": "country46",
        "region": "region46",
        "cityName": "cityName46",
        "postalCode": "postalCode46",
        "streetName": "streetName46"
    },
    {
        "businessPartnerId": "oyjQqWJDbxHQuapnvISdnFebRNGRHjXQ",
        "name1": "name147",
        "name2": "name247",
        "name3": "name347",
        "name4": "name447",
        "emailAddress": "emailAddress47",
        "phoneNumber": "phoneNumber47",
        "cellPhoneNumber": "cellPhoneNumber47",
        "faxNumber": "faxNumber47",
        "country": "country47",
        "region": "region47",
        "cityName": "cityName47",
        "postalCode": "postalCode47",
        "streetName": "streetName47"
    },
    {
        "businessPartnerId": "kYJvkwRjnFABeMIOmboeAUKbdittieEL",
        "name1": "name148",
        "name2": "name248",
        "name3": "name348",
        "name4": "name448",
        "emailAddress": "emailAddress48",
        "phoneNumber": "phoneNumber48",
        "cellPhoneNumber": "cellPhoneNumber48",
        "faxNumber": "faxNumber48",
        "country": "country48",
        "region": "region48",
        "cityName": "cityName48",
        "postalCode": "postalCode48",
        "streetName": "streetName48"
    },
    {
        "businessPartnerId": "hFQBsMXeYGMjFXVATHOpHgoHbeovUTCY",
        "name1": "name149",
        "name2": "name249",
        "name3": "name349",
        "name4": "name449",
        "emailAddress": "emailAddress49",
        "phoneNumber": "phoneNumber49",
        "cellPhoneNumber": "cellPhoneNumber49",
        "faxNumber": "faxNumber49",
        "country": "country49",
        "region": "region49",
        "cityName": "cityName49",
        "postalCode": "postalCode49",
        "streetName": "streetName49"
    },
    {
        "businessPartnerId": "VcPaFkSEYOmbjrXxqxzBMrcPEQMlPltJ",
        "name1": "name150",
        "name2": "name250",
        "name3": "name350",
        "name4": "name450",
        "emailAddress": "emailAddress50",
        "phoneNumber": "phoneNumber50",
        "cellPhoneNumber": "cellPhoneNumber50",
        "faxNumber": "faxNumber50",
        "country": "country50",
        "region": "region50",
        "cityName": "cityName50",
        "postalCode": "postalCode50",
        "streetName": "streetName50"
    },
    {
        "businessPartnerId": "IwTyGuLCVFPPLtHSuScsBdejDZQdOowq",
        "name1": "name151",
        "name2": "name251",
        "name3": "name351",
        "name4": "name451",
        "emailAddress": "emailAddress51",
        "phoneNumber": "phoneNumber51",
        "cellPhoneNumber": "cellPhoneNumber51",
        "faxNumber": "faxNumber51",
        "country": "country51",
        "region": "region51",
        "cityName": "cityName51",
        "postalCode": "postalCode51",
        "streetName": "streetName51"
    },
    {
        "businessPartnerId": "bGNxYHBAICYRJPdSSQyfRygqaCCYdzlT",
        "name1": "name152",
        "name2": "name252",
        "name3": "name352",
        "name4": "name452",
        "emailAddress": "emailAddress52",
        "phoneNumber": "phoneNumber52",
        "cellPhoneNumber": "cellPhoneNumber52",
        "faxNumber": "faxNumber52",
        "country": "country52",
        "region": "region52",
        "cityName": "cityName52",
        "postalCode": "postalCode52",
        "streetName": "streetName52"
    },
    {
        "businessPartnerId": "AJQfTBRQuGiQWubhFrEoTJVpNEvKjZPV",
        "name1": "name153",
        "name2": "name253",
        "name3": "name353",
        "name4": "name453",
        "emailAddress": "emailAddress53",
        "phoneNumber": "phoneNumber53",
        "cellPhoneNumber": "cellPhoneNumber53",
        "faxNumber": "faxNumber53",
        "country": "country53",
        "region": "region53",
        "cityName": "cityName53",
        "postalCode": "postalCode53",
        "streetName": "streetName53"
    },
    {
        "businessPartnerId": "LRvuphEUkdLYHXVbgCurBLyCjbtKQnog",
        "name1": "name154",
        "name2": "name254",
        "name3": "name354",
        "name4": "name454",
        "emailAddress": "emailAddress54",
        "phoneNumber": "phoneNumber54",
        "cellPhoneNumber": "cellPhoneNumber54",
        "faxNumber": "faxNumber54",
        "country": "country54",
        "region": "region54",
        "cityName": "cityName54",
        "postalCode": "postalCode54",
        "streetName": "streetName54"
    },
    {
        "businessPartnerId": "KZyDqxNcoaDebfFZeDsWYGrVVciNgLKN",
        "name1": "name155",
        "name2": "name255",
        "name3": "name355",
        "name4": "name455",
        "emailAddress": "emailAddress55",
        "phoneNumber": "phoneNumber55",
        "cellPhoneNumber": "cellPhoneNumber55",
        "faxNumber": "faxNumber55",
        "country": "country55",
        "region": "region55",
        "cityName": "cityName55",
        "postalCode": "postalCode55",
        "streetName": "streetName55"
    },
    {
        "businessPartnerId": "HFQKNGQFIIiaxNOwlBgkSJpbgFPDcCJz",
        "name1": "name156",
        "name2": "name256",
        "name3": "name356",
        "name4": "name456",
        "emailAddress": "emailAddress56",
        "phoneNumber": "phoneNumber56",
        "cellPhoneNumber": "cellPhoneNumber56",
        "faxNumber": "faxNumber56",
        "country": "country56",
        "region": "region56",
        "cityName": "cityName56",
        "postalCode": "postalCode56",
        "streetName": "streetName56"
    },
    {
        "businessPartnerId": "NarGSGCKtfYEBchfsIHqIuUiaCnaaEXb",
        "name1": "name157",
        "name2": "name257",
        "name3": "name357",
        "name4": "name457",
        "emailAddress": "emailAddress57",
        "phoneNumber": "phoneNumber57",
        "cellPhoneNumber": "cellPhoneNumber57",
        "faxNumber": "faxNumber57",
        "country": "country57",
        "region": "region57",
        "cityName": "cityName57",
        "postalCode": "postalCode57",
        "streetName": "streetName57"
    },
    {
        "businessPartnerId": "JhyNLHPMlOWATCBxXqryUYCQHNVoOGiB",
        "name1": "name158",
        "name2": "name258",
        "name3": "name358",
        "name4": "name458",
        "emailAddress": "emailAddress58",
        "phoneNumber": "phoneNumber58",
        "cellPhoneNumber": "cellPhoneNumber58",
        "faxNumber": "faxNumber58",
        "country": "country58",
        "region": "region58",
        "cityName": "cityName58",
        "postalCode": "postalCode58",
        "streetName": "streetName58"
    },
    {
        "businessPartnerId": "HsWArJnwujFJidRYkELujwmeCkMXAxzG",
        "name1": "name159",
        "name2": "name259",
        "name3": "name359",
        "name4": "name459",
        "emailAddress": "emailAddress59",
        "phoneNumber": "phoneNumber59",
        "cellPhoneNumber": "cellPhoneNumber59",
        "faxNumber": "faxNumber59",
        "country": "country59",
        "region": "region59",
        "cityName": "cityName59",
        "postalCode": "postalCode59",
        "streetName": "streetName59"
    },
    {
        "businessPartnerId": "rnlalGgVzTBZriFVwMQXOjEThWnnGmGe",
        "name1": "name160",
        "name2": "name260",
        "name3": "name360",
        "name4": "name460",
        "emailAddress": "emailAddress60",
        "phoneNumber": "phoneNumber60",
        "cellPhoneNumber": "cellPhoneNumber60",
        "faxNumber": "faxNumber60",
        "country": "country60",
        "region": "region60",
        "cityName": "cityName60",
        "postalCode": "postalCode60",
        "streetName": "streetName60"
    },
    {
        "businessPartnerId": "fsgVCpBKwdALDpDhfPruQaJQVTbjebSO",
        "name1": "name161",
        "name2": "name261",
        "name3": "name361",
        "name4": "name461",
        "emailAddress": "emailAddress61",
        "phoneNumber": "phoneNumber61",
        "cellPhoneNumber": "cellPhoneNumber61",
        "faxNumber": "faxNumber61",
        "country": "country61",
        "region": "region61",
        "cityName": "cityName61",
        "postalCode": "postalCode61",
        "streetName": "streetName61"
    },
    {
        "businessPartnerId": "xbnENtVTsNmyIgFwYipIRwpcJzFcIpbi",
        "name1": "name162",
        "name2": "name262",
        "name3": "name362",
        "name4": "name462",
        "emailAddress": "emailAddress62",
        "phoneNumber": "phoneNumber62",
        "cellPhoneNumber": "cellPhoneNumber62",
        "faxNumber": "faxNumber62",
        "country": "country62",
        "region": "region62",
        "cityName": "cityName62",
        "postalCode": "postalCode62",
        "streetName": "streetName62"
    },
    {
        "businessPartnerId": "YnlHWDrsYAUIDCjFlDNMUzMzcQkVnJBo",
        "name1": "name163",
        "name2": "name263",
        "name3": "name363",
        "name4": "name463",
        "emailAddress": "emailAddress63",
        "phoneNumber": "phoneNumber63",
        "cellPhoneNumber": "cellPhoneNumber63",
        "faxNumber": "faxNumber63",
        "country": "country63",
        "region": "region63",
        "cityName": "cityName63",
        "postalCode": "postalCode63",
        "streetName": "streetName63"
    },
    {
        "businessPartnerId": "AYfMBnYFUyoaFHHdHNLmPcyUtEjMBKCV",
        "name1": "name164",
        "name2": "name264",
        "name3": "name364",
        "name4": "name464",
        "emailAddress": "emailAddress64",
        "phoneNumber": "phoneNumber64",
        "cellPhoneNumber": "cellPhoneNumber64",
        "faxNumber": "faxNumber64",
        "country": "country64",
        "region": "region64",
        "cityName": "cityName64",
        "postalCode": "postalCode64",
        "streetName": "streetName64"
    },
    {
        "businessPartnerId": "MXDYhEdJhgYZpmqBWbAtcyAkFwXBDABv",
        "name1": "name165",
        "name2": "name265",
        "name3": "name365",
        "name4": "name465",
        "emailAddress": "emailAddress65",
        "phoneNumber": "phoneNumber65",
        "cellPhoneNumber": "cellPhoneNumber65",
        "faxNumber": "faxNumber65",
        "country": "country65",
        "region": "region65",
        "cityName": "cityName65",
        "postalCode": "postalCode65",
        "streetName": "streetName65"
    },
    {
        "businessPartnerId": "DAfEoEAaGgmCedwOUuViJwCIhidQXmHv",
        "name1": "name166",
        "name2": "name266",
        "name3": "name366",
        "name4": "name466",
        "emailAddress": "emailAddress66",
        "phoneNumber": "phoneNumber66",
        "cellPhoneNumber": "cellPhoneNumber66",
        "faxNumber": "faxNumber66",
        "country": "country66",
        "region": "region66",
        "cityName": "cityName66",
        "postalCode": "postalCode66",
        "streetName": "streetName66"
    },
    {
        "businessPartnerId": "UuXkZiFjSRZPYmsWFiOoHKxcquzvLLDr",
        "name1": "name167",
        "name2": "name267",
        "name3": "name367",
        "name4": "name467",
        "emailAddress": "emailAddress67",
        "phoneNumber": "phoneNumber67",
        "cellPhoneNumber": "cellPhoneNumber67",
        "faxNumber": "faxNumber67",
        "country": "country67",
        "region": "region67",
        "cityName": "cityName67",
        "postalCode": "postalCode67",
        "streetName": "streetName67"
    },
    {
        "businessPartnerId": "YaaWETCwoFETXCjlBMnbnPLytLppIFfI",
        "name1": "name168",
        "name2": "name268",
        "name3": "name368",
        "name4": "name468",
        "emailAddress": "emailAddress68",
        "phoneNumber": "phoneNumber68",
        "cellPhoneNumber": "cellPhoneNumber68",
        "faxNumber": "faxNumber68",
        "country": "country68",
        "region": "region68",
        "cityName": "cityName68",
        "postalCode": "postalCode68",
        "streetName": "streetName68"
    },
    {
        "businessPartnerId": "LEGAlGjBeRWowaYJKimuPCvezqCfWLkR",
        "name1": "name169",
        "name2": "name269",
        "name3": "name369",
        "name4": "name469",
        "emailAddress": "emailAddress69",
        "phoneNumber": "phoneNumber69",
        "cellPhoneNumber": "cellPhoneNumber69",
        "faxNumber": "faxNumber69",
        "country": "country69",
        "region": "region69",
        "cityName": "cityName69",
        "postalCode": "postalCode69",
        "streetName": "streetName69"
    },
    {
        "businessPartnerId": "hFBShhqnPLfhCbqvGvPrCWVwuqvlfpBe",
        "name1": "name170",
        "name2": "name270",
        "name3": "name370",
        "name4": "name470",
        "emailAddress": "emailAddress70",
        "phoneNumber": "phoneNumber70",
        "cellPhoneNumber": "cellPhoneNumber70",
        "faxNumber": "faxNumber70",
        "country": "country70",
        "region": "region70",
        "cityName": "cityName70",
        "postalCode": "postalCode70",
        "streetName": "streetName70"
    },
    {
        "businessPartnerId": "yPVhksYruigZOBSNpTtzwemSJsVqaklk",
        "name1": "name171",
        "name2": "name271",
        "name3": "name371",
        "name4": "name471",
        "emailAddress": "emailAddress71",
        "phoneNumber": "phoneNumber71",
        "cellPhoneNumber": "cellPhoneNumber71",
        "faxNumber": "faxNumber71",
        "country": "country71",
        "region": "region71",
        "cityName": "cityName71",
        "postalCode": "postalCode71",
        "streetName": "streetName71"
    },
    {
        "businessPartnerId": "WkrnnGqKlaFPTxgbpVCSWnORSXZKtQOf",
        "name1": "name172",
        "name2": "name272",
        "name3": "name372",
        "name4": "name472",
        "emailAddress": "emailAddress72",
        "phoneNumber": "phoneNumber72",
        "cellPhoneNumber": "cellPhoneNumber72",
        "faxNumber": "faxNumber72",
        "country": "country72",
        "region": "region72",
        "cityName": "cityName72",
        "postalCode": "postalCode72",
        "streetName": "streetName72"
    },
    {
        "businessPartnerId": "yLpwSYWIgzRByaAdXYDEJQRUdStxfWcj",
        "name1": "name173",
        "name2": "name273",
        "name3": "name373",
        "name4": "name473",
        "emailAddress": "emailAddress73",
        "phoneNumber": "phoneNumber73",
        "cellPhoneNumber": "cellPhoneNumber73",
        "faxNumber": "faxNumber73",
        "country": "country73",
        "region": "region73",
        "cityName": "cityName73",
        "postalCode": "postalCode73",
        "streetName": "streetName73"
    },
    {
        "businessPartnerId": "rXRFDfpPdmeObdOxYuIpuHbmzixRgEjx",
        "name1": "name174",
        "name2": "name274",
        "name3": "name374",
        "name4": "name474",
        "emailAddress": "emailAddress74",
        "phoneNumber": "phoneNumber74",
        "cellPhoneNumber": "cellPhoneNumber74",
        "faxNumber": "faxNumber74",
        "country": "country74",
        "region": "region74",
        "cityName": "cityName74",
        "postalCode": "postalCode74",
        "streetName": "streetName74"
    },
    {
        "businessPartnerId": "PkEbbbWJyGfpIkQrpZHSXNNtBVAhANyS",
        "name1": "name175",
        "name2": "name275",
        "name3": "name375",
        "name4": "name475",
        "emailAddress": "emailAddress75",
        "phoneNumber": "phoneNumber75",
        "cellPhoneNumber": "cellPhoneNumber75",
        "faxNumber": "faxNumber75",
        "country": "country75",
        "region": "region75",
        "cityName": "cityName75",
        "postalCode": "postalCode75",
        "streetName": "streetName75"
    },
    {
        "businessPartnerId": "pjSvHClHPQLOrgoYXNsgXifzYtujHqpB",
        "name1": "name176",
        "name2": "name276",
        "name3": "name376",
        "name4": "name476",
        "emailAddress": "emailAddress76",
        "phoneNumber": "phoneNumber76",
        "cellPhoneNumber": "cellPhoneNumber76",
        "faxNumber": "faxNumber76",
        "country": "country76",
        "region": "region76",
        "cityName": "cityName76",
        "postalCode": "postalCode76",
        "streetName": "streetName76"
    },
    {
        "businessPartnerId": "MxunfeIxdOujeBGwXKAtnLUcrEvpHkjE",
        "name1": "name177",
        "name2": "name277",
        "name3": "name377",
        "name4": "name477",
        "emailAddress": "emailAddress77",
        "phoneNumber": "phoneNumber77",
        "cellPhoneNumber": "cellPhoneNumber77",
        "faxNumber": "faxNumber77",
        "country": "country77",
        "region": "region77",
        "cityName": "cityName77",
        "postalCode": "postalCode77",
        "streetName": "streetName77"
    },
    {
        "businessPartnerId": "CfhmpHCybORNePkJoWHdKsgGKZHwFxkC",
        "name1": "name178",
        "name2": "name278",
        "name3": "name378",
        "name4": "name478",
        "emailAddress": "emailAddress78",
        "phoneNumber": "phoneNumber78",
        "cellPhoneNumber": "cellPhoneNumber78",
        "faxNumber": "faxNumber78",
        "country": "country78",
        "region": "region78",
        "cityName": "cityName78",
        "postalCode": "postalCode78",
        "streetName": "streetName78"
    },
    {
        "businessPartnerId": "eUmIYcUNVmrNoscmyqwvUITQBxUAvNQH",
        "name1": "name179",
        "name2": "name279",
        "name3": "name379",
        "name4": "name479",
        "emailAddress": "emailAddress79",
        "phoneNumber": "phoneNumber79",
        "cellPhoneNumber": "cellPhoneNumber79",
        "faxNumber": "faxNumber79",
        "country": "country79",
        "region": "region79",
        "cityName": "cityName79",
        "postalCode": "postalCode79",
        "streetName": "streetName79"
    },
    {
        "businessPartnerId": "pidkCkzHMwmXIHzUgyrpjeIpmtbcNnpE",
        "name1": "name180",
        "name2": "name280",
        "name3": "name380",
        "name4": "name480",
        "emailAddress": "emailAddress80",
        "phoneNumber": "phoneNumber80",
        "cellPhoneNumber": "cellPhoneNumber80",
        "faxNumber": "faxNumber80",
        "country": "country80",
        "region": "region80",
        "cityName": "cityName80",
        "postalCode": "postalCode80",
        "streetName": "streetName80"
    },
    {
        "businessPartnerId": "FAezYJitClpzRxYhntSHwswjacDZnIdW",
        "name1": "name181",
        "name2": "name281",
        "name3": "name381",
        "name4": "name481",
        "emailAddress": "emailAddress81",
        "phoneNumber": "phoneNumber81",
        "cellPhoneNumber": "cellPhoneNumber81",
        "faxNumber": "faxNumber81",
        "country": "country81",
        "region": "region81",
        "cityName": "cityName81",
        "postalCode": "postalCode81",
        "streetName": "streetName81"
    },
    {
        "businessPartnerId": "mIWfwhEDaYUxiapspnRPFXXZrQJayywE",
        "name1": "name182",
        "name2": "name282",
        "name3": "name382",
        "name4": "name482",
        "emailAddress": "emailAddress82",
        "phoneNumber": "phoneNumber82",
        "cellPhoneNumber": "cellPhoneNumber82",
        "faxNumber": "faxNumber82",
        "country": "country82",
        "region": "region82",
        "cityName": "cityName82",
        "postalCode": "postalCode82",
        "streetName": "streetName82"
    }
]